ansys/dpf/post/__init__.py
ansys/dpf/post/common.py
ansys/dpf/post/connectivity.py
ansys/dpf/post/dataframe.py
ansys/dpf/post/displacement.py
ansys/dpf/post/dpf_path.py
ansys/dpf/post/dpf_solution.py
ansys/dpf/post/electric_results.py
ansys/dpf/post/elements.py
ansys/dpf/post/errors.py
ansys/dpf/post/faces.py
ansys/dpf/post/fluid_simulation.py
ansys/dpf/post/harmonic_analysis.py
ansys/dpf/post/harmonic_mechanical_simulation.py
ansys/dpf/post/index.py
ansys/dpf/post/mesh.py
ansys/dpf/post/mesh_info.py
ansys/dpf/post/meshes.py
ansys/dpf/post/misc.py
ansys/dpf/post/misc_results.py
ansys/dpf/post/modal_analysis.py
ansys/dpf/post/modal_mechanical_simulation.py
ansys/dpf/post/named_selection.py
ansys/dpf/post/nodes.py
ansys/dpf/post/phase.py
ansys/dpf/post/post_utility.py
ansys/dpf/post/result_data.py
ansys/dpf/post/result_definition.py
ansys/dpf/post/result_evaluation.py
ansys/dpf/post/result_object.py
ansys/dpf/post/scalar.py
ansys/dpf/post/selection.py
ansys/dpf/post/simulation.py
ansys/dpf/post/species.py
ansys/dpf/post/static_analysis.py
ansys/dpf/post/static_mechanical_simulation.py
ansys/dpf/post/strain.py
ansys/dpf/post/stress.py
ansys/dpf/post/temperature.py
ansys/dpf/post/tensor.py
ansys/dpf/post/tools.py
ansys/dpf/post/transient_analysis.py
ansys/dpf/post/transient_mechanical_simulation.py
ansys/dpf/post/vector.py
ansys/dpf/post/examples/__init__.py
ansys/dpf/post/helpers/__init__.py
ansys/dpf/post/helpers/selections.py
ansys/dpf/post/helpers/streamlines.py
ansys/dpf/post/result_workflows/_build_workflow.py
ansys/dpf/post/result_workflows/_component_helper.py
ansys/dpf/post/result_workflows/_connect_workflow_inputs.py
ansys/dpf/post/result_workflows/_sub_workflows.py
ansys/dpf/post/result_workflows/_utils.py
ansys_dpf_post-0.10.1.dist-info/licenses/LICENSE
ansys_dpf_post-0.10.1.dist-info/WHEEL
ansys_dpf_post-0.10.1.dist-info/METADATA
ansys_dpf_post-0.10.1.dist-info/RECORD
