Metadata-Version: 2.4
Name: ansys-dpf-post
Version: 0.10.1
Summary: PyDPF-Post Python library.
Author-email: "ANSYS, Inc." <pyansys.core@ansys.com>
Maintainer-email: "ANSYS, Inc." <pyansys.core@ansys.com>
Requires-Python: >=3.9,<4.0
License-Expression: MIT
Classifier: Development Status :: 4 - Beta
Classifier: Intended Audience :: Science/Research
Classifier: Operating System :: MacOS
Classifier: Operating System :: Microsoft :: Windows
Classifier: Operating System :: POSIX
Classifier: Programming Language :: Python :: 3.9
Classifier: Programming Language :: Python :: 3.10
Classifier: Programming Language :: Python :: 3.11
Classifier: Programming Language :: Python :: 3.12
Classifier: Topic :: Scientific/Engineering :: Information Analysis
License-File: LICENSE
Requires-Dist: ansys-dpf-core
Requires-Dist: scooby
Requires-Dist: pyvista>=0.24.0 ; extra == "graphics"
Requires-Dist: pyvista>=0.24.0 ; extra == "plotting"
Project-URL: Source, https://github.com/ansys/pydpf-post
Provides-Extra: graphics
Provides-Extra: plotting
